KEL/__init__.py
KEL/Engine/__init__.py
KEL/Engine/Components/__init__.py
KEL/Engine/Components/moveWallComp.py
KEL/Engine/Components/renderRectComp.py
KEL/Engine/Components/transformRectComp.py
KEL/Engine/Const/__init__.py
KEL/Engine/Const/colors.py
KEL/Engine/Const/const.py
KEL/Engine/Core/__init__.py
KEL/Engine/Core/core.py
KEL/Engine/Core/event.py
KEL/Engine/Core/input.py
KEL/Engine/Core/rawInput.py
KEL/Engine/Game/__init__.py
KEL/Engine/Game/game.py
KEL/Engine/Game/pygameSetup.py
KEL/Engine/Maths/__init__.py
KEL/Engine/Maths/maths.py
KEL/Engine/Models/__init__.py
KEL/Engine/Models/emptyModel.py
KEL/UI/__init__.py
Engine_KEL-0.0.4.dist-info/METADATA
Engine_KEL-0.0.4.dist-info/WHEEL
Engine_KEL-0.0.4.dist-info/top_level.txt
Engine_KEL-0.0.4.dist-info/RECORD
