Metadata-Version: 2.1
Name: Engine-KEL
Version: 0.0.4
Summary: A Simple Game Engine Libary
Home-page: UNKNOWN
Author: Sixten Bohman
Author-email: sixten.bohman.08@gmail.com
License: UNKNOWN
Keywords: python,pygame,Game Engine,Simple,Beginner,Learning
Platform: UNKNOWN
Classifier: Development Status :: 1 - Planning
Classifier: Intended Audience :: Developers
Classifier: Programming Language :: Python :: 3
Classifier: Operating System :: Unix
Classifier: Operating System :: MacOS :: MacOS X
Classifier: Operating System :: Microsoft :: Windows
Requires-Dist: pygame
